{
  "project_info": {
    "project_number": "540805121210",
    "firebase_url": "https://face-detector-22c47.firebaseio.com",
    "project_id": "face-detector-22c47",
    "storage_bucket": "face-detector-22c47.appspot.com"
  },
  "client": [
    {
      "client_info": {
        "mobilesdk_app_id": "1:540805121210:android:cf268c775b076a87bcee83",
        "android_client_info": {
          "package_name": "tk.advaitkale.facedetection"
        }
      },
      "oauth_client": [
        {
          "client_id": "540805121210-i6ucjg4u5mrsu1plfs2au5u7bsp6smid.apps.googleusercontent.com",
          "client_type": 3
        }
      ],
      "api_key": [
        {
          "current_key": "AIzaSyDXfxOfAww8EmyDjTUuoFVvXKIcFRrDkW0"
        }
      ],
      "services": {
        "appinvite_service": {
          "other_platform_oauth_client": [
            {
              "client_id": "540805121210-i6ucjg4u5mrsu1plfs2au5u7bsp6smid.apps.googleusercontent.com",
              "client_type": 3
            }
          ]
        }
      }
    }
  ],
  "configuration_version": "1"
}